Workbook

Sheet Assumptions
A1: DoublYellow — Financial Model Assumptions
A2: Blue = input | Black = formula | Edit blue cells to run scenarios
A3: Assumption | B3: Year 1 | C3: Year 2 | D3: Year 3 | E3: Notes
A4: USER GROWTH
A5: Starting active users (base) | B5: 500 | C5: 5000 | D5: 30000 | E5: Conservative scenario
A6: Peak active users (year-end) | B6: 5000 | C6: 30000 | D6: 150000 | E6: Conservative scenario
A7: Average MAU (mid-point used) | B7: 2750 | C7: 17500 | D7: 90000 | E7: (start+end)/2
A8: Premium conversion rate (%) | B8: 0.05 | C8: 0.08 | D8: 0.12 | E8: 5-12% is typical freemium
A9: Avg premium MAU | B9: 138 | C9: 1400 | D9: 10800 | E9: MAU × conversion rate
A10: REVENUE — SUBSCRIPTIONS
A11: Monthly subscription price (£) | B11: 2.99 | C11: 2.99 | D11: 2.99 | E11: £2.99/mo launch price
A12: Annual subscription price (£) | B12: 24.99 | C12: 24.99 | D12: 24.99 | E12: £24.99/yr (save ~30%)
A13: % subscribers on annual plan | B13: 0.3 | C13: 0.35 | D13: 0.4 | E13: Annual better for cash flow
A14: Effective monthly ARPU (£) | B14: 2.74 | C14: 2.69 | D14: 2.64 | E14: blended: mo+(ann/12)×mix
A15: REVENUE — ADVERTISING
A16: Ad-supported DAU (free tier) | B16: 2612 | C16: 16100 | D16: 79200 | E16: MAU × 0.95 × 0.5 DAU ratio
A17: eCPM (£ per 1,000 impressions) | B17: 1.5 | C17: 1.8 | D17: 2.2 | E17: UK geo premium
A18: Ad impressions per DAU per day | B18: 3 | C18: 3 | D18: 3 | E18: 3 banner/interstitial/day
A19: COST ASSUMPTIONS
A20: Supabase (database+auth) / mo (£) | B20: 50 | C20: 200 | D20: 600 | E20: Pro plan scales
A21: RevenueCat IAP fee (% of sub rev) | B21: 0.01 | C21: 0.01 | D21: 0.01 | E21: ~1% after first $2.5k/mo
A22: App store fee (% of sub rev) | B22: 0.3 | C22: 0.3 | D22: 0.3 | E22: Apple/Google 30% (15% small dev yr1)
A23: Push notifications (OneSignal) / mo | B23: 0 | C23: 0 | D23: 99 | E23: Free up to 10k subs
A24: Marketing spend (from investment £) | B24: 80000 | C24: 40000 | D24: 60000 | E24: £80k Y1 from raise
A25: Dev / tech contractor costs (£/yr) | B25: 32000 | C25: 24000 | D25: 48000 | E25: From investment Y1
A26: Toby salary (£/yr) | B26: 0 | C26: 30000 | D26: 45000 | E26: Y1 sweat equity
A27: Legal / admin / accountancy (£/yr) | B27: 5000 | C27: 6000 | D27: 8000
A28: Other overheads (£/yr) | B28: 3000 | C28: 5000 | D28: 8000 | E28: domain, tools, misc
A29: INVESTMENT
A30: Investment raised (£) | B30: 150000 | C30: 0 | D30: 0 | E30: £150k seed round
A31: Equity given (%) | B31: 0.1 | C31: 0 | D31: 0 | E31: 10% to investors
A32: Pre-money valuation (£) | B32: 1350000 | C32: 0 | D32: 0 | E32: £1.35M pre-money

Sheet P&L
A1: DoublYellow — Profit & Loss Projection (Years 1–3)
A2: All figures in GBP (£). Figures derived from Assumptions sheet. Green = formula. Blue = hardcode.
B3: Year 1 | C3: Year 2 | D3: Year 3 | E3: Notes
A4: REVENUE
A5: Subscription revenue | B5: =Assumptions!B9*Assumptions!B14*12 -> 4537.44 | C5: =Assumptions!C9*Assumptions!C14*12 -> 45192 | D5: =Assumptions!D9*Assumptions!D14*12 -> 342144 | E5: Avg premium MAU × ARPU × 12
A6: Advertising revenue | B6: =Assumptions!B16*Assumptions!B17/1000*Assumptions!B18*365 -> 4290.21 | C6: =Assumptions!C16*Assumptions!C17/1000*Assumptions!C18*365 -> 31733.1 | D6: =Assumptions!D16*Assumptions!D17/1000*Assumptions!D18*365 -> 190792.8 | E6: DAU × eCPM/1000 × impr/day × 365
A7: TOTAL REVENUE | B7: =SUM(B5:B6) -> 8827.65 | C7: =SUM(C5:C6) -> 76925.1 | D7: =SUM(D5:D6) -> 532936.8
A9: COST OF REVENUE (COGS)
A10: Supabase (database & auth) | B10: =Assumptions!B20*12 -> 600 | C10: =Assumptions!C20*12 -> 2400 | D10: =Assumptions!D20*12 -> 7200 | E10: Monthly fee × 12
A11: RevenueCat IAP platform fee | B11: =B5*Assumptions!B21 -> 45.3744 | C11: =C5*Assumptions!C21 -> 451.92 | D11: =D5*Assumptions!D21 -> 3421.44 | E11: ~1% of sub revenue
A12: App store commission (Apple/Google) | B12: =B5*Assumptions!B22 -> 1361.232 | C12: =C5*Assumptions!C22 -> 13557.6 | D12: =D5*Assumptions!D22 -> 102643.2 | E12: 30% of sub rev (15% small dev)
A13: Push notifications (OneSignal) | B13: =Assumptions!B23*12 -> 0 | C13: =Assumptions!C23*12 -> 0 | D13: =Assumptions!D23*12 -> 1188 | E13: Free to 10k, then paid
A14: TOTAL COGS | B14: =SUM(B10:B13) -> 2006.6064 | C14: =SUM(C10:C13) -> 16409.52 | D14: =SUM(D10:D13) -> 114452.64
A16: GROSS PROFIT | B16: =B7-B14 -> 6821.0436 | C16: =C7-C14 -> 60515.58 | D16: =D7-D14 -> 418484.16
A17: Gross margin (%) | B17: =IF(B7=0,0,B16/B7) -> 0.77269076 | C17: =IF(C7=0,0,C16/C7) -> 0.78668185 | D17: =IF(D7=0,0,D16/D7) -> 0.78524163 | E17: Gross profit ÷ total revenue
A19: OPERATING EXPENSES (OPEX)
A20: Marketing & user acquisition | B20: =Assumptions!B24 -> 80000 | C20: =Assumptions!C24 -> 40000 | D20: =Assumptions!D24 -> 60000 | E20: £80k Y1 from raise
A21: Dev / tech contractor costs | B21: =Assumptions!B25 -> 32000 | C21: =Assumptions!C25 -> 24000 | D21: =Assumptions!D25 -> 48000 | E21: £32k Y1 from raise
A22: Toby salary | B22: =Assumptions!B26 -> 0 | C22: =Assumptions!C26 -> 30000 | D22: =Assumptions!D26 -> 45000 | E22: Y1 = £0 sweat equity
A23: Legal / admin / accountancy | B23: =Assumptions!B27 -> 5000 | C23: =Assumptions!C27 -> 6000 | D23: =Assumptions!D27 -> 8000
A24: Other overheads | B24: =Assumptions!B28 -> 3000 | C24: =Assumptions!C28 -> 5000 | D24: =Assumptions!D28 -> 8000 | E24: Domain, tools, misc
A25: TOTAL OPEX | B25: =SUM(B20:B24) -> 120000 | C25: =SUM(C20:C24) -> 105000 | D25: =SUM(D20:D24) -> 169000
A27: EBITDA (Operating profit/loss) | B27: =B16-B25 -> -113178.96 | C27: =C16-C25 -> -44484.42 | D27: =D16-D25 -> 249484.16
A28: EBITDA margin (%) | B28: =IF(B7=0,0,B27/B7) -> -12.820961 | C28: =IF(C7=0,0,C27/C7) -> -0.57828225 | D28: =IF(D7=0,0,D27/D7) -> 0.46813086 | E28: EBITDA ÷ total revenue
A30: BELOW THE LINE
A31: Tax (corporation tax ~19%) | B31: =IF(B27>0,B27*0.19,0) -> 0 | C31: =IF(C27>0,C27*0.19,0) -> 0 | D31: =IF(D27>0,D27*0.19,0) -> 47401.99 | E31: Only if profitable; 19% CT
A33: NET PROFIT / (LOSS) | B33: =B27-B31 -> -113178.96 | C33: =C27-C31 -> -44484.42 | D33: =D27-D31 -> 202082.17
A34: Net margin (%) | B34: =IF(B7=0,0,B33/B7) -> -12.820961 | C34: =IF(C7=0,0,C33/C7) -> -0.57828225 | D34: =IF(D7=0,0,D33/D7) -> 0.37918599 | E34: Net profit ÷ total revenue
A36: CASH POSITION
A37: Opening cash | B37: =Assumptions!B30 -> 150000 | C37: =B38 -> 36821.044 | D37: =C38 -> -7663.3764 | E37: Y1 = investment raised
A38: Closing cash (opening + net profit) | B38: =B37+B33 -> 36821.044 | C38: =C37+C33 -> -7663.3764 | D38: =D37+D33 -> 194418.79 | E38: Runway indicator

Sheet Scenarios
A1: DoublYellow — Scenario Comparison (Year 1 Snapshot)
A2: Metric | B2: Bear Case | D2: Base Case | F2: Bull Case | I2: Notes
A3: Active users Y1 (avg) | B3: 1000 | D3: 2750 | F3: 6000
A4: Premium conv. rate | B4: 0.03 | D4: 0.05 | F4: 0.08
A5: Avg premium MAU | B5: 30 | D5: 138 | F5: 480
A6: ARPU (blended £/mo) | B6: 2.74 | D6: 2.74 | F6: 2.99
A7: Sub revenue (£) | B7: =B5*B4*12 -> 10.8 | D7: =D5*D4*12 -> 82.8 | F7: =F5*F4*12 -> 460.8
A8: Ad revenue (£) | B8: 4000 | D8: 5200 | F8: 12000
A9: TOTAL REVENUE | B9: =B6+B7 -> 13.54 | D9: =D6+D7 -> 85.54 | F9: =F6+F7 -> 463.79
A10: COGS (£) | B10: 2000 | D10: 3600 | F10: 8500
A11: GROSS PROFIT | B11: =B8-B9 -> 3986.46 | D11: =D8-D9 -> 5114.46 | F11: =F8-F9 -> 11536.21
A12: OPEX (£) | B12: 120000 | D12: 120000 | F12: 120000
A13: EBITDA | B13: =B10-B11 -> -1986.46 | D13: =D10-D11 -> -1514.46 | F13: =F10-F11 -> -3036.21
A14: Investment cash | B14: 150000 | D14: 150000 | F14: 150000
A15: Closing cash | B15: =B13+B12 -> 118013.54 | D15: =D13+D12 -> 118485.54 | F15: =F13+F12 -> 116963.79
